[
  {
    "pid": "130081606",
    "title": "Shupogaki",
    "author": "Aviary",
    "url": "https://i.pixiv.cat/img-original/img/2025/05/06/00/00/03/130081606_p0.png",
    "source": "Pixiv"
  },
  {
    "pid": "130124502",
    "title": "Hikari, Nozomi",
    "author": "真",
    "url": "https://i.pixiv.cat/img-original/img/2025/05/07/00/00/18/130124502_p0.png",
    "source": "Pixiv"
  },
  {
    "pid": "130124502",
    "title": "Hikari, Nozomi",
    "author": "真",
    "url": "https://i.pixiv.cat/img-original/img/2025/05/07/00/00/18/130124502_p1.png",
    "source": "Pixiv"
  },
  {
    "pid": "130285174",
    "title": "ヒカリ＆ノゾミ",
    "author": "水道炒飯",
    "url": "https://i.pixiv.cat/img-original/img/2025/05/11/13/29/46/130285174_p0.jpg",
    "source": "Pixiv"
  },
  {
    "pid": "130445677",
    "title": "こどもの日",
    "author": "fungus",
    "url": "https://i.pixiv.cat/img-original/img/2025/05/16/00/00/08/130445677_p0.jpg",
    "source": "Pixiv"
  },
  {
    "pid": "135406620",
    "title": "Hikari",
    "author": "Poko",
    "url": "https://i.pixiv.cat/img-original/img/2025/09/22/17/35/28/135406620_p0.jpg",
    "source": "Pixiv"
  },
  {
    "pid": "135915022",
    "title": "ヒカリとハンバーガーデート🍔♡",
    "author": "みこし",
    "url": "https://i.pixiv.cat/img-original/img/2025/10/05/20/07/51/135915022_p0.jpg",
    "source": "Pixiv"
  },
  {
    "pid": "136813906",
    "title": "Yostar OFFCIAL SHOP グッズ用イラスト",
    "author": "にんげんまめ￤2日目東ア-31",
    "url": "https://i.pixiv.cat/img-original/img/2025/10/29/00/00/17/136813906_p0.jpg",
    "source": "Pixiv"
  },
  {
    "pid": "138125740",
    "title": "help~",
    "author": "SeeRo",
    "url": "https://i.pixiv.cat/img-original/img/2025/12/02/00/11/00/138125740_p0.png",
    "source": "Pixiv"
  },
  {
    "pid": "138161003",
    "title": "🎪🚆",
    "author": "PELLas",
    "url": "https://i.pixiv.cat/img-original/img/2025/12/03/00/00/28/138161003_p0.png",
    "source": "Pixiv"
  },
  {
    "pid": "138161003",
    "title": "🎪🚆",
    "author": "PELLas",
    "url": "https://i.pixiv.cat/img-original/img/2025/12/03/00/00/28/138161003_p1.png",
    "source": "Pixiv"
  },
  {
    "pid": "138448344",
    "title": "明星ヒマリ🌌",
    "author": "NoriMori",
    "url": "https://i.pixiv.cat/img-original/img/2025/12/10/20/15/03/138448344_p0.jpg",
    "source": "Pixiv"
  },
  {
    "pid": "132516267",
    "title": "シロコ",
    "author": "smong",
    "url": "https://i.pixiv.cat/img-original/img/2025/07/10/03/30/21/132516267_p0.png",
    "source": "Pixiv"
  },
  {
    "pid": "140869722",
    "title": "风过留痕",
    "author": "pluie",
    "url": "https://i.pixiv.cat/img-original/img/2026/02/07/10/32/22/140869722_p0.png",
    "source": "Pixiv"
  },
  {
    "pid": "130592804",
    "title": "Shiroko",
    "author": "Maybe",
    "url": "https://i.pixiv.cat/img-original/img/2025/05/19/22/02/42/130592804_p0.png",
    "source": "Pixiv"
  },
  {
    "pid": "135424283",
    "title": "白子在教室里干啥呢？",
    "author": "晓潇pumpit",
    "url": "https://i.pixiv.cat/img-original/img/2025/09/23/00/35/37/135424283_p0.jpg",
    "source": "Pixiv"
  },
  {
    "pid": "142209409",
    "title": "ヒナ",
    "author": "Applepie/AP",
    "url": "https://i.pixiv.cat/img-original/img/2026/03/12/18/18/45/142209409_p0.jpg",
    "source": "Pixiv"
  },
  {
    "pid": "141778609",
    "title": "mika nagi seia",
    "author": "Evande",
    "url": "https://i.pixiv.cat/img-original/img/2026/03/01/17/10/53/141778609_p0.png",
    "source": "Pixiv"
  },
  {
    "pid": "135843208",
    "title": "砂狼シロコ",
    "author": "圆子ako",
    "url": "https://i.pixiv.cat/img-original/img/2025/10/04/01/14/04/135843208_p0.png",
    "source": "Pixiv"
  },
  {
    "pid": "141897693",
    "title": "思い出の中の笑顔",
    "author": "猫屋(NEKOYA)",
    "url": "https://i.pixiv.cat/img-original/img/2026/03/04/18/06/22/141897693_p0.png",
    "source": "Pixiv"
  },
  {
    "pid": "142807495",
    "title": "餞",
    "author": "かぼみーる",
    "url": "https://i.pixiv.cat/img-original/img/2026/03/27/19/42/12/142807495_p0.jpg",
    "source": "Pixiv"
  },
  {
    "pid": "142155537",
    "title": "画了白子",
    "author": "Yuye",
    "url": "https://i.pixiv.cat/img-original/img/2026/03/11/02/15/09/142155537_p0.jpg",
    "source": "Pixiv"
  },
  {
    "pid": "142743623",
    "title": "FOX 小隊 🫶",
    "author": "Giga-Tera",
    "url": "https://i.pixiv.cat/img-original/img/2026/03/26/17/29/38/142743623_p0.png",
    "source": "Pixiv"
  },
  {
    "pid": "141857641",
    "title": "ドレスのヒナちゃんとデート！",
    "author": "フェルネモ",
    "url": "https://i.pixiv.cat/img-original/img/2026/03/03/16/59/16/141857641_p0.png",
    "source": "Pixiv"
  },
  {
    "pid": "142709682",
    "title": "🤍",
    "author": "アイス",
    "url": "https://i.pixiv.cat/img-original/img/2026/03/25/01/57/51/142709682_p0.png",
    "source": "Pixiv"
  },
  {
    "pid": "113927215",
    "title": "アイドルアロナとプラナ✨",
    "author": "KMP",
    "url": "https://i.pixiv.cat/img-original/img/2023/12/03/21/25/20/113927215_p0.jpg",
    "source": "Pixiv"
  },
  {
    "pid": "124018611",
    "title": "무제",
    "author": "W.J",
    "url": "https://i.pixiv.cat/img-original/img/2024/11/05/14/55/03/124018611_p0.png",
    "source": "Pixiv"
  },
  {
    "pid": "128959993",
    "title": "紡ぐ四季に彩りを",
    "author": "彩ゆき",
    "url": "https://i.pixiv.cat/img-original/img/2025/04/05/00/08/46/128959993_p0.jpg",
    "source": "Pixiv"
  },
  {
    "pid": "128159890",
    "title": "( •̀ ω •́ )y",
    "author": "咔咔",
    "url": "https://i.pixiv.cat/img-original/img/2025/03/13/13/44/29/128159890_p0.jpg",
    "source": "Pixiv"
  },
  {
    "pid": "125578889",
    "title": "阿罗娜&普拉娜（25/30）",
    "author": "千代明Kira",
    "url": "https://i.pixiv.cat/img-original/img/2024/12/27/00/45/35/125578889_p0.png",
    "source": "Pixiv"
  },
  {
    "pid": "115800992",
    "title": "アロナ",
    "author": "白-Hyacinth",
    "url": "https://i.pixiv.cat/img-original/img/2024/02/06/00/33/39/115800992_p0.jpg",
    "source": "Pixiv"
  },
  {
    "pid": "117433743",
    "title": "アロプラ",
    "author": "のっけ",
    "url": "https://i.pixiv.cat/img-original/img/2024/04/01/00/00/03/117433743_p0.jpg",
    "source": "Pixiv"
  },
  {
    "pid": "132568767",
    "title": "100 プラナ",
    "author": "アサハル",
    "url": "https://i.pixiv.cat/img-original/img/2025/07/11/17/51/31/132568767_p0.jpg",
    "source": "Pixiv"
  },
  {
    "pid": "134351577",
    "title": "アロプラ",
    "author": "しもにきたけし",
    "url": "https://i.pixiv.cat/img-original/img/2025/08/26/17/49/19/134351577_p0.png",
    "source": "Pixiv"
  },
  {
    "pid": "129694183",
    "title": "阿罗娜",
    "author": "叶明",
    "url": "https://i.pixiv.cat/img-original/img/2025/04/25/22/50/12/129694183_p0.png",
    "source": "Pixiv"
  },
  {
    "pid": "115226775",
    "title": "AROPRA",
    "author": "HJ_penguin",
    "url": "https://i.pixiv.cat/img-original/img/2024/01/16/22/12/16/115226775_p0.png",
    "source": "Pixiv"
  },
  {
    "pid": "140002737",
    "title": "プラナ",
    "author": "白糸",
    "url": "https://i.pixiv.cat/img-original/img/2026/01/16/18/49/40/140002737_p0.jpg",
    "source": "Pixiv"
  },
  {
    "pid": "112929242",
    "title": "プラナ",
    "author": "RangToRi@FANBOX",
    "url": "https://i.pixiv.cat/img-original/img/2023/10/29/00/00/21/112929242_p0.png",
    "source": "Pixiv"
  },
  {
    "pid": "113310289",
    "title": "イズナ",
    "author": "にんげんまめ￤2日目東ア-31",
    "url": "https://i.pixiv.cat/img-original/img/2023/11/11/09/17/57/113310289_p0.png",
    "source": "Pixiv"
  },
  {
    "pid": "141083010",
    "title": "セナ",
    "author": "BBARU",
    "url": "https://i.pixiv.cat/img-original/img/2026/02/12/18/59/47/141083010_p0.png",
    "source": "Pixiv"
  },
  {
    "pid": "135791779",
    "title": "32日目",
    "author": "殘夜 ZANYA",
    "url": "https://i.pixiv.cat/img-original/img/2025/10/02/19/30/01/135791779_p0.jpg",
    "source": "Pixiv"
  },
  {
    "pid": "139029643",
    "title": "🛷",
    "author": "Rega",
    "url": "https://i.pixiv.cat/img-original/img/2025/12/25/12/03/11/139029643_p0.jpg",
    "source": "Pixiv"
  },
  {
    "pid": "141251465",
    "title": "0216",
    "author": "Okkimon",
    "url": "https://i.pixiv.cat/img-original/img/2026/02/16/12/52/48/141251465_p0.jpg",
    "source": "Pixiv"
  },
  {
    "pid": "134693642",
    "title": "板垣 庚(地雷系)",
    "author": "Re_NAYA南言",
    "url": "https://i.pixiv.cat/img-original/img/2025/09/04/10/15/51/134693642_p0.jpg",
    "source": "Pixiv"
  },
  {
    "pid": "134693642",
    "title": "板垣 庚(地雷系)",
    "author": "Re_NAYA南言",
    "url": "https://i.pixiv.cat/img-original/img/2025/09/04/10/15/51/134693642_p1.jpg",
    "source": "Pixiv"
  },
  {
    "pid": "134874694",
    "title": "무제",
    "author": "Von",
    "url": "https://i.pixiv.cat/img-original/img/2025/09/08/23/23/28/134874694_p0.jpg",
    "source": "Pixiv"
  },
  {
    "pid": "141912042",
    "title": "ミヨの日",
    "author": "さぐらだ",
    "url": "https://i.pixiv.cat/img-original/img/2026/03/05/00/00/04/141912042_p0.jpg",
    "source": "Pixiv"
  },
  {
    "pid": "139319952",
    "title": "待ち時間💭",
    "author": "なむなむ",
    "url": "https://i.pixiv.cat/img-original/img/2025/12/31/19/33/32/139319952_p0.png",
    "source": "Pixiv"
  },
  {
    "pid": "131889258",
    "title": "メロンソーダ、めっちゃおいしい！",
    "author": "Muo",
    "url": "https://i.pixiv.cat/img-original/img/2025/06/23/18/00/10/131889258_p0.png",
    "source": "Pixiv"
  },
  {
    "pid": "133663819",
    "title": "コユキ(ナイトプール)",
    "author": "ももいもん",
    "url": "https://i.pixiv.cat/img-original/img/2025/08/09/13/09/18/133663819_p0.jpg",
    "source": "Pixiv"
  },
  {
    "pid": "134707136",
    "title": "2日目",
    "author": "殘夜 ZANYA",
    "url": "https://i.pixiv.cat/img-original/img/2025/09/04/20/04/00/134707136_p0.jpg",
    "source": "Pixiv"
  },
  {
    "pid": "135176362",
    "title": "16日目",
    "author": "殘夜 ZANYA",
    "url": "https://i.pixiv.cat/img-original/img/2025/09/16/19/45/21/135176362_p0.jpg",
    "source": "Pixiv"
  },
  {
    "pid": "135931650",
    "title": "ミヨ",
    "author": "Kamoru",
    "url": "https://i.pixiv.cat/img-original/img/2025/10/06/02/10/41/135931650_p0.png",
    "source": "Pixiv"
  },
  {
    "pid": "136422400",
    "title": "48日目",
    "author": "殘夜 ZANYA",
    "url": "https://i.pixiv.cat/img-original/img/2025/10/18/19/30/01/136422400_p0.jpg",
    "source": "Pixiv"
  },
  {
    "pid": "136555025",
    "title": "无题",
    "author": "絆",
    "url": "https://i.pixiv.cat/img-original/img/2025/10/22/01/29/27/136555025_p0.jpg",
    "source": "Pixiv"
  },
  {
    "pid": "136874763",
    "title": "頭をぐいぐい押し付けてくるアロナ",
    "author": "夏うに",
    "url": "https://i.pixiv.cat/img-original/img/2025/10/30/19/30/01/136874763_p0.jpg",
    "source": "Pixiv"
  },
  {
    "pid": "138921136",
    "title": "ホシノ",
    "author": "モ誰",
    "url": "https://i.pixiv.cat/img-original/img/2025/12/23/00/00/03/138921136_p0.jpg",
    "source": "Pixiv"
  },
  {
    "pid": "121236368",
    "title": "体操服ユウカ",
    "author": "らんけぶ ⚓︎",
    "url": "https://i.pixiv.cat/img-original/img/2024/08/08/08/09/37/121236368_p0.png",
    "source": "Pixiv"
  },
  {
    "pid": "137736014",
    "title": "冬のユウカ",
    "author": "Mellozzo",
    "url": "https://i.pixiv.cat/img-original/img/2025/11/22/00/00/25/137736014_p0.png",
    "source": "Pixiv"
  },
  {
    "pid": "136395690",
    "title": "秤アツコ",
    "author": "sikimosh",
    "url": "https://i.pixiv.cat/img-original/img/2025/10/18/00/48/37/136395690_p0.jpg",
    "source": "Pixiv"
  },
  {
    "pid": "133678510",
    "title": "ユウカにブラッシング",
    "author": "胡乱茶",
    "url": "https://i.pixiv.cat/img-original/img/2025/08/09/20/55/31/133678510_p0.jpg",
    "source": "Pixiv"
  },
  {
    "pid": "134385484",
    "title": "yuuka",
    "author": "lan9798",
    "url": "https://i.pixiv.cat/img-original/img/2025/08/27/16/04/49/134385484_p0.jpg",
    "source": "Pixiv"
  },
  {
    "pid": "109817371",
    "title": "优香",
    "author": "桐野",
    "url": "https://i.pixiv.cat/img-original/img/2023/07/11/11/12/26/109817371_p0.jpg",
    "source": "Pixiv"
  },
  {
    "pid": "135391518",
    "title": "無題",
    "author": "isana615",
    "url": "https://i.pixiv.cat/img-original/img/2025/09/22/04/12/28/135391518_p0.png",
    "source": "Pixiv"
  },
  {
    "pid": "136491391",
    "title": "老师，在吗？嘟~",
    "author": "诗言",
    "url": "https://i.pixiv.cat/img-original/img/2025/10/20/09/52/30/136491391_p0.png",
    "source": "Pixiv"
  },
  {
    "pid": "124901856",
    "title": "ミサキ",
    "author": "南条まや",
    "url": "https://i.pixiv.cat/img-original/img/2024/12/05/00/00/12/124901856_p0.jpg",
    "source": "Pixiv"
  },
  {
    "pid": "134840563",
    "title": "模写",
    "author": "こぽ",
    "url": "https://i.pixiv.cat/img-original/img/2025/09/08/00/17/06/134840563_p0.jpg",
    "source": "Pixiv"
  },
  {
    "pid": "136061023",
    "title": "スバル先輩",
    "author": "しもうみ@お仕事募集中",
    "url": "https://i.pixiv.cat/img-original/img/2025/10/09/18/08/17/136061023_p0.png",
    "source": "Pixiv"
  },
  {
    "pid": "137777969",
    "title": "スバル",
    "author": "えなが",
    "url": "https://i.pixiv.cat/img-original/img/2025/11/23/00/34/57/137777969_p0.jpg",
    "source": "Pixiv"
  },
  {
    "pid": "137716642",
    "title": "梯スバル",
    "author": "しノり",
    "url": "https://i.pixiv.cat/img-original/img/2025/11/21/14/20/28/137716642_p0.jpg",
    "source": "Pixiv"
  },
  {
    "pid": "137430483",
    "title": "ヒカリ",
    "author": "しノり",
    "url": "https://i.pixiv.cat/img-original/img/2025/11/13/20/27/14/137430483_p0.jpg",
    "source": "Pixiv"
  },
  {
    "pid": "135845889",
    "title": "ヒカリ",
    "author": "당나커／ダナコ",
    "url": "https://i.pixiv.cat/img-original/img/2025/10/04/03/01/50/135845889_p0.jpg",
    "source": "Pixiv"
  },
  {
    "pid": "135465805",
    "title": "ノゾミ",
    "author": "당나커／ダナコ",
    "url": "https://i.pixiv.cat/img-original/img/2025/09/24/00/48/46/135465805_p0.jpg",
    "source": "Pixiv"
  },
  {
    "pid": "117778928",
    "title": "シュポガキ3",
    "author": "Toast bun",
    "url": "https://i.pixiv.cat/img-original/img/2024/04/12/22/32/13/117778928_p0.jpg",
    "source": "Pixiv"
  },
  {
    "pid": "132698696",
    "title": "Wオーバーオール",
    "author": "Tam-U",
    "url": "https://i.pixiv.cat/img-original/img/2025/07/14/21/42/22/132698696_p0.png",
    "source": "Pixiv"
  },
  {
    "pid": "135248139",
    "title": "忘れられたアビドスの駅にて。",
    "author": "はいね*",
    "url": "https://i.pixiv.cat/img-original/img/2025/09/18/19/08/27/135248139_p0.png",
    "source": "Pixiv"
  },
  {
    "pid": "130519981",
    "title": "診察室へどうぞ",
    "author": "房",
    "url": "https://i.pixiv.cat/img-original/img/2025/05/18/00/00/13/130519981_p0.png",
    "source": "Pixiv"
  },
  {
    "pid": "130500072",
    "title": "😠💢",
    "author": "mojo",
    "url": "https://i.pixiv.cat/img-original/img/2025/06/12/14/30/02/130500072_p0.png",
    "source": "Pixiv"
  },
  {
    "pid": "130295433",
    "title": "ハイランダー",
    "author": "IKKY",
    "url": "https://i.pixiv.cat/img-original/img/2025/05/11/18/53/34/130295433_p0.jpg",
    "source": "Pixiv"
  },
  {
    "pid": "129195635",
    "title": "DAY 9 ヒカリ",
    "author": "okutiri",
    "url": "https://i.pixiv.cat/img-original/img/2025/04/12/09/54/27/129195635_p0.png",
    "source": "Pixiv"
  },
  {
    "pid": "135960217",
    "title": "ホシノ",
    "author": "okutiri",
    "url": "https://i.pixiv.cat/img-original/img/2025/10/06/22/23/17/135960217_p0.png",
    "source": "Pixiv"
  },
  {
    "pid": "142339533",
    "title": "冬の夜 / Winter Night",
    "author": "汐",
    "url": "https://i.pixiv.cat/img-original/img/2026/03/15/20/55/06/142339533_p0.png",
    "source": "Pixiv"
  },
  {
    "pid": "122223861",
    "title": "制服シロコ*テラー",
    "author": "みるるん",
    "url": "https://i.pixiv.cat/img-original/img/2024/09/07/20/58/57/122223861_p0.png",
    "source": "Pixiv"
  },
  {
    "pid": "123933858",
    "title": "ん、先生　座って",
    "author": "みるるん",
    "url": "https://i.pixiv.cat/img-original/img/2024/11/02/22/04/02/123933858_p0.png",
    "source": "Pixiv"
  },
  {
    "pid": "142617338",
    "title": "砂狼 シロコ＊テラー",
    "author": "Deflection",
    "url": "https://i.pixiv.cat/img-original/img/2026/03/22/19/57/56/142617338_p0.png",
    "source": "Pixiv"
  },
  {
    "pid": "133359770",
    "title": "砂すな狼おおかみ シロコ",
    "author": "dongle",
    "url": "https://i.pixiv.cat/img-original/img/2025/08/01/17/35/05/133359770_p0.jpg",
    "source": "Pixiv"
  },
  {
    "pid": "133648431",
    "title": "Sunaōkami Shiroko",
    "author": "TORETTA",
    "url": "https://i.pixiv.cat/img-original/img/2025/08/09/00/46/29/133648431_p0.jpg",
    "source": "Pixiv"
  },
  {
    "pid": "96319112",
    "title": "シロコ",
    "author": "空雪",
    "url": "https://i.pixiv.cat/img-original/img/2022/02/17/16/13/39/96319112_p0.png",
    "source": "Pixiv"
  },
  {
    "pid": "112984776",
    "title": "ハイキングシロコ",
    "author": "山田アウト",
    "url": "https://i.pixiv.cat/img-original/img/2023/10/30/22/13/03/112984776_p0.png",
    "source": "Pixiv"
  },
  {
    "pid": "138824370",
    "title": "无题",
    "author": "清汤",
    "url": "https://i.pixiv.cat/img-original/img/2025/12/20/18/44/58/138824370_p0.jpg",
    "source": "Pixiv"
  },
  {
    "pid": "111305746",
    "title": "砂狼シロコ",
    "author": "秋澪",
    "url": "https://i.pixiv.cat/img-original/img/2023/08/31/01/04/43/111305746_p0.png",
    "source": "Pixiv"
  },
  {
    "pid": "137487925",
    "title": "シロコちゃん",
    "author": "萌橙🍀",
    "url": "https://i.pixiv.cat/img-original/img/2025/11/15/09/20/16/137487925_p0.jpg",
    "source": "Pixiv"
  },
  {
    "pid": "140285848",
    "title": "「ん…先生、おはよう」",
    "author": "汐",
    "url": "https://i.pixiv.cat/img-original/img/2026/01/23/20/52/38/140285848_p0.png",
    "source": "Pixiv"
  },
  {
    "pid": "140285848",
    "title": "「ん…先生、おはよう」",
    "author": "汐",
    "url": "https://i.pixiv.cat/img-original/img/2026/01/23/20/52/38/140285848_p0.png",
    "source": "Pixiv"
  },
  {
    "pid": "141515086",
    "title": "カヨコ",
    "author": "shiitakee",
    "url": "https://i.pixiv.cat/img-original/img/2026/02/23/01/51/17/141515086_p0.png",
    "source": "Pixiv"
  },
  {
    "pid": "133555309",
    "title": "day37 遥香",
    "author": "砂粒shali",
    "url": "https://i.pixiv.cat/img-original/img/2025/08/06/17/17/17/133555309_p0.jpg",
    "source": "Pixiv"
  },
  {
    "pid": "129516480",
    "title": "Haruka",
    "author": "萝卜姬",
    "url": "https://i.pixiv.cat/img-original/img/2025/04/20/19/19/58/129516480_p0.jpg",
    "source": "Pixiv"
  },
  {
    "pid": "138404275",
    "title": "アル",
    "author": "JW",
    "url": "https://i.pixiv.cat/img-original/img/2025/12/09/15/32/18/138404275_p0.jpg",
    "source": "Pixiv"
  },
  {
    "pid": "128111822",
    "title": "陸八魔アル",
    "author": "Varlyn",
    "url": "https://i.pixiv.cat/img-original/img/2025/03/12/00/00/18/128111822_p0.jpg",
    "source": "Pixiv"
  },
  {
    "pid": "141857555",
    "title": "フウカたそとデート！",
    "author": "フェルネモ",
    "url": "https://i.pixiv.cat/img-original/img/2026/03/03/16/54/49/141857555_p0.jpg",
    "source": "Pixiv"
  },
  {
    "pid": "141657841",
    "title": "ケイ🩷🤍",
    "author": "kaerunrun",
    "url": "https://i.pixiv.cat/img-original/img/2026/02/26/19/24/21/141657841_p0.png",
    "source": "Pixiv"
  },
  {
    "pid": "142443312",
    "title": "欢迎回来，sensei~",
    "author": "鲭鱼けけ",
    "url": "https://i.pixiv.cat/img-original/img/2026/03/18/14/37/55/142443312_p0.png",
    "source": "Pixiv"
  },
  {
    "pid": "140458396",
    "title": "ケイ",
    "author": "サンロクス",
    "url": "https://i.pixiv.cat/img-original/img/2026/01/28/01/39/03/140458396_p0.jpg",
    "source": "Pixiv"
  },
  {
    "pid": "133214806",
    "title": "マリー(アイドル)",
    "author": "SWOON",
    "url": "https://i.pixiv.cat/img-original/img/2025/07/28/17/38/24/133214806_p0.png",
    "source": "Pixiv"
  },
  {
    "pid": "142781230",
    "title": "Soft Smile Among Blossoms",
    "author": "ResCat",
    "url": "https://i.pixiv.cat/img-original/img/2026/03/27/00/02/18/142781230_p0.png",
    "source": "Pixiv"
  },
  {
    "pid": "142627576",
    "title": "无题",
    "author": "Reisakiz_",
    "url": "https://i.pixiv.cat/img-original/img/2026/03/22/23/09/39/142627576_p0.jpg",
    "source": "Pixiv"
  },
  {
    "pid": "140842675",
    "title": "メイドマリー",
    "author": "よしはる",
    "url": "https://i.pixiv.cat/img-original/img/2026/02/06/19/32/07/140842675_p0.png",
    "source": "Pixiv"
  },
  {
    "pid": "129012404",
    "title": "伊落マリー",
    "author": "냥나링",
    "url": "https://i.pixiv.cat/img-original/img/2025/04/06/12/04/51/129012404_p0.jpg",
    "source": "Pixiv"
  },
  {
    "pid": "135791594",
    "title": "伊落マリー",
    "author": "やー",
    "url": "https://i.pixiv.cat/img-original/img/2025/10/02/19/23/47/135791594_p0.jpg",
    "source": "Pixiv"
  },
  {
    "pid": "130276223",
    "title": "伊落 マリー",
    "author": "みやヨキ",
    "url": "https://i.pixiv.cat/img-original/img/2025/05/11/06/54/47/130276223_p0.png",
    "source": "Pixiv"
  },
  {
    "pid": "127502724",
    "title": "マリー",
    "author": "桐喏ToUNo🍡",
    "url": "https://i.pixiv.cat/img-original/img/2025/02/22/12/52/52/127502724_p0.png",
    "source": "Pixiv"
  },
  {
    "pid": "128574797",
    "title": "寝起きマリー",
    "author": "夕兎",
    "url": "https://i.pixiv.cat/img-original/img/2025/03/25/00/31/56/128574797_p0.png",
    "source": "Pixiv"
  },
  {
    "pid": "131250104",
    "title": "体操服玛丽",
    "author": "鹿汐chiyo",
    "url": "https://i.pixiv.cat/img-original/img/2025/06/06/21/48/03/131250104_p0.jpg",
    "source": "Pixiv"
  },
  {
    "pid": "111291955",
    "title": "いっしょに",
    "author": "Muo",
    "url": "https://i.pixiv.cat/img-original/img/2023/08/30/18/02/47/111291955_p0.jpg",
    "source": "Pixiv"
  },
  {
    "pid": "135751711",
    "title": "🍉🍉🍉",
    "author": "Muo",
    "url": "https://i.pixiv.cat/img-original/img/2025/10/01/18/00/15/135751711_p0.png",
    "source": "Pixiv"
  },
  {
    "pid": "137052137",
    "title": "MARI",
    "author": "Muo",
    "url": "https://i.pixiv.cat/img-original/img/2025/11/03/18/00/14/137052137_p0.png",
    "source": "Pixiv"
  },
  {
    "pid": "139486792",
    "title": "浦和ハナコ",
    "author": "梨",
    "url": "https://i.pixiv.cat/img-original/img/2026/01/03/23/56/46/139486792_p0.png",
    "source": "Pixiv"
  },
  {
    "pid": "117219785",
    "title": "无题",
    "author": "真理-Mari",
    "url": "https://i.pixiv.cat/img-original/img/2024/03/25/14/33/00/117219785_p0.png",
    "source": "Pixiv"
  },
  {
    "pid": "130371996",
    "title": "ノア",
    "author": "ラムジ",
    "url": "https://i.pixiv.cat/img-original/img/2025/05/13/21/53/38/130371996_p0.png",
    "source": "Pixiv"
  },
  {
    "pid": "128255458",
    "title": "Day 1 诺亚",
    "author": "JEI",
    "url": "https://i.pixiv.cat/img-original/img/2025/03/16/00/57/52/128255458_p0.png",
    "source": "Pixiv"
  },
  {
    "pid": "127021199",
    "title": "パジャマノア",
    "author": "とんかつ",
    "url": "https://i.pixiv.cat/img-original/img/2025/02/08/16/25/07/127021199_p0.png",
    "source": "Pixiv"
  },
  {
    "pid": "139175151",
    "title": "ミレニアム地下鉄",
    "author": "niagara",
    "url": "https://i.pixiv.cat/img-original/img/2025/12/28/15/57/24/139175151_p0.jpg",
    "source": "Pixiv"
  },
  {
    "pid": "127131546",
    "title": "無題",
    "author": "ひろい空hiroi sora",
    "url": "https://i.pixiv.cat/img-original/img/2025/02/11/18/23/40/127131546_p0.png",
    "source": "Pixiv"
  },
  {
    "pid": "133376095",
    "title": "リオと過ごす夏🌻",
    "author": "Mellozzo",
    "url": "https://i.pixiv.cat/img-original/img/2025/08/02/00/00/23/133376095_p0.png",
    "source": "Pixiv"
  },
  {
    "pid": "137209690",
    "title": "CM",
    "author": "Rega",
    "url": "https://i.pixiv.cat/img-original/img/2025/11/08/00/00/15/137209690_p0.jpg",
    "source": "Pixiv"
  },
  {
    "pid": "130124538",
    "title": "💤",
    "author": "雪/yuki",
    "url": "https://i.pixiv.cat/img-original/img/2025/05/07/00/00/23/130124538_p0.jpg",
    "source": "Pixiv"
  },
  {
    "pid": "125629401",
    "title": "先生..?",
    "author": "Rega",
    "url": "https://i.pixiv.cat/img-original/img/2024/12/28/17/27/08/125629401_p0.jpg",
    "source": "Pixiv"
  },
  {
    "pid": "114247653",
    "title": "リオ",
    "author": "ももいもん",
    "url": "https://i.pixiv.cat/img-original/img/2023/12/15/19/00/01/114247653_p0.jpg",
    "source": "Pixiv"
  },
  {
    "pid": "109138754",
    "title": "ロリオ",
    "author": "雪/yuki",
    "url": "https://i.pixiv.cat/img-original/img/2023/06/19/00/00/56/109138754_p0.jpg",
    "source": "Pixiv"
  },
  {
    "pid": "114533666",
    "title": "(^///^)",
    "author": "雪/yuki",
    "url": "https://i.pixiv.cat/img-original/img/2023/12/25/12/05/22/114533666_p0.jpg",
    "source": "Pixiv"
  },
  {
    "pid": "110616177",
    "title": "「先生、これは必要な出費だよ」",
    "author": "Hood",
    "url": "https://i.pixiv.cat/img-original/img/2023/08/07/19/13/41/110616177_p0.png",
    "source": "Pixiv"
  },
  {
    "pid": "138352929",
    "title": "お姉ちゃんちょっと黙ってて！",
    "author": "おぐら",
    "url": "https://i.pixiv.cat/img-original/img/2025/12/08/00/51/54/138352929_p0.png",
    "source": "Pixiv"
  },
  {
    "pid": "140357150",
    "title": "THE GOAT",
    "author": "U.Rang",
    "url": "https://i.pixiv.cat/img-original/img/2026/01/25/14/30/01/140357150_p0.jpg",
    "source": "Pixiv"
  },
  {
    "pid": "140761270",
    "title": "ゲーム開発部　バレンタイン準備中",
    "author": "shooka C104参加",
    "url": "https://i.pixiv.cat/img-original/img/2026/02/04/17/21/28/140761270_p0.jpg",
    "source": "Pixiv"
  },
  {
    "pid": "115478297",
    "title": "歌う猫を拾ったよ、先生。",
    "author": "Nasan",
    "url": "https://i.pixiv.cat/img-original/img/2024/01/25/22/55/44/115478297_p0.jpg",
    "source": "Pixiv"
  },
  {
    "pid": "100454769",
    "title": "ん…完熟…",
    "author": "Nasan",
    "url": "https://i.pixiv.cat/img-original/img/2022/08/13/18/25/03/100454769_p0.jpg",
    "source": "Pixiv"
  },
  {
    "pid": "113002187",
    "title": "ホシノ",
    "author": "SuperPig",
    "url": "https://i.pixiv.cat/img-original/img/2023/10/31/11/55/48/113002187_p0.png",
    "source": "Pixiv"
  },
  {
    "pid": "105466693",
    "title": "ヒナ",
    "author": "라베/ラーベ",
    "url": "https://i.pixiv.cat/img-original/img/2023/02/17/20/23/52/105466693_p0.jpg",
    "source": "Pixiv"
  },
  {
    "pid": "88174527",
    "title": "ソラちゃんメモロビ",
    "author": "荻pote",
    "url": "https://i.pixiv.cat/img-original/img/2021/03/03/00/00/27/88174527_p0.jpg",
    "source": "Pixiv"
  },
  {
    "pid": "88472450",
    "title": "先生…大丈夫…？",
    "author": "こゆびた べる▶お仕事募集中",
    "url": "https://i.pixiv.cat/img-original/img/2021/03/15/19/22/38/88472450_p0.jpg",
    "source": "Pixiv"
  },
  {
    "pid": "137986221",
    "title": "そのスリッパ、何？😐✨",
    "author": "ラテちゃん / LatteS2",
    "url": "https://i.pixiv.cat/img-original/img/2025/11/28/18/00/52/137986221_p0.png",
    "source": "Pixiv"
  },
  {
    "pid": "108669534",
    "title": "ムツキと…",
    "author": "どんえふ",
    "url": "https://i.pixiv.cat/img-original/img/2023/06/03/00/07/18/108669534_p0.jpg",
    "source": "Pixiv"
  },
  {
    "pid": "121382069",
    "title": "ウイ",
    "author": "SuperPig",
    "url": "https://i.pixiv.cat/img-original/img/2024/08/11/10/30/01/121382069_p0.png",
    "source": "Pixiv"
  },
  {
    "pid": "101974989",
    "title": "ムツキ",
    "author": "SuperPig",
    "url": "https://i.pixiv.cat/img-original/img/2022/10/16/09/10/59/101974989_p0.png",
    "source": "Pixiv"
  },
  {
    "pid": "112688409",
    "title": "优胜！！！",
    "author": "Ruilur",
    "url": "https://i.pixiv.cat/img-original/img/2023/10/20/01/12/27/112688409_p0.jpg",
    "source": "Pixiv"
  },
  {
    "pid": "136106342",
    "title": "やっほ～！せ～んせいっ！",
    "author": "小鳥遊あすと / Astro",
    "url": "https://i.pixiv.cat/img-original/img/2025/10/10/21/04/40/136106342_p0.jpg",
    "source": "Pixiv"
  },
  {
    "pid": "134217950",
    "title": "浅黄ムツキ2",
    "author": "NESS",
    "url": "https://i.pixiv.cat/img-original/img/2025/08/23/08/33/21/134217950_p0.jpg",
    "source": "Pixiv"
  },
  {
    "pid": "126576155",
    "title": "무제",
    "author": "HEDO",
    "url": "https://i.pixiv.cat/img-original/img/2025/01/26/14/01/13/126576155_p0.png",
    "source": "Pixiv"
  },
  {
    "pid": "133795071",
    "title": "フウカ",
    "author": "アオトーメイ@fanbox",
    "url": "https://i.pixiv.cat/img-original/img/2025/08/12/17/03/09/133795071_p0.jpg",
    "source": "Pixiv"
  },
  {
    "pid": "124026416",
    "title": "フウカ",
    "author": "朽ち袖",
    "url": "https://i.pixiv.cat/img-original/img/2024/11/05/20/50/44/124026416_p0.png",
    "source": "Pixiv"
  },
  {
    "pid": "120279381",
    "title": "空崎ヒナ 😴",
    "author": "blance💙ブランす",
    "url": "https://i.pixiv.cat/img-original/img/2024/07/06/09/35/24/120279381_p0.jpg",
    "source": "Pixiv"
  },
  {
    "pid": "127895748",
    "title": "私服フウカ",
    "author": "朽ち袖",
    "url": "https://i.pixiv.cat/img-original/img/2025/03/05/20/43/56/127895748_p0.png",
    "source": "Pixiv"
  },
  {
    "pid": "130078431",
    "title": "シュポガキ（ヒカリ&ノゾミ）",
    "author": "朽ち袖",
    "url": "https://i.pixiv.cat/img-original/img/2025/05/05/22/49/04/130078431_p0.png",
    "source": "Pixiv"
  },
  {
    "pid": "134080298",
    "title": "なでなでプリーズ、ほめてほめてー",
    "author": "なし🍐",
    "url": "https://i.pixiv.cat/img-original/img/2025/08/19/18/58/41/134080298_p0.jpg",
    "source": "Pixiv"
  },
  {
    "pid": "129917290",
    "title": "ヒカノゾ",
    "author": "だいふく",
    "url": "https://i.pixiv.cat/img-original/img/2025/05/01/21/53/06/129917290_p0.jpg",
    "source": "Pixiv"
  },
  {
    "pid": "129917290",
    "title": "ヒカノゾ",
    "author": "だいふく",
    "url": "https://i.pixiv.cat/img-original/img/2025/05/01/21/53/06/129917290_p0.jpg",
    "source": "Pixiv"
  },
  {
    "pid": "139468963",
    "title": "お別れの時間",
    "author": "niagara",
    "url": "https://i.pixiv.cat/img-original/img/2026/01/03/17/24/45/139468963_p0.jpg",
    "source": "Pixiv"
  },
  {
    "pid": "131300157",
    "title": "小塗 マキ (キャンプ)",
    "author": "Moo",
    "url": "https://i.pixiv.cat/img-original/img/2025/06/08/01/17/21/131300157_p0.png",
    "source": "Pixiv"
  },
  {
    "pid": "142729244",
    "title": "真夜中",
    "author": "鲭鱼けけ",
    "url": "https://i.pixiv.cat/img-original/img/2026/03/25/18/27/12/142729244_p0.jpg",
    "source": "Pixiv"
  },
  {
    "pid": "126396941",
    "title": "【ブルーアーカイブ４周年記念イラスト】マキ＆ウタハ＆コトリ",
    "author": "東暮 Higashigure",
    "url": "https://i.pixiv.cat/img-original/img/2025/01/20/12/00/16/126396941_p0.jpg",
    "source": "Pixiv"
  },
  {
    "pid": "120498537",
    "title": "なつ！！",
    "author": "ﾍﾅﾁｮｺ",
    "url": "https://i.pixiv.cat/img-original/img/2024/07/13/21/42/36/120498537_p0.jpg",
    "source": "Pixiv"
  },
  {
    "pid": "125660786",
    "title": "好想喝水。。",
    "author": "添弓",
    "url": "https://i.pixiv.cat/img-original/img/2025/01/04/17/48/19/125660786_p0.jpg",
    "source": "Pixiv"
  },
  {
    "pid": "98398587",
    "title": "29日目,砂狼シロコ",
    "author": "モ誰",
    "url": "https://i.pixiv.cat/img-original/img/2022/05/17/00/00/10/98398587_p0.jpg",
    "source": "Pixiv"
  },
  {
    "pid": "115540123",
    "title": "うめっ",
    "author": "ﾍﾅﾁｮｺ",
    "url": "https://i.pixiv.cat/img-original/img/2024/01/28/01/25/29/115540123_p0.jpg",
    "source": "Pixiv"
  },
  {
    "pid": "121801937",
    "title": "補習授業部",
    "author": "M1z",
    "url": "https://i.pixiv.cat/img-original/img/2024/08/25/00/00/18/121801937_p0.jpg",
    "source": "Pixiv"
  },
  {
    "pid": "132069140",
    "title": "天童 アリス",
    "author": "椿A",
    "url": "https://i.pixiv.cat/img-original/img/2025/06/28/17/51/16/132069140_p0.jpg",
    "source": "Pixiv"
  },
  {
    "pid": "112635024",
    "title": "アロナ",
    "author": "高橋羽音Takahashi",
    "url": "https://i.pixiv.cat/img-original/img/2023/10/17/23/39/43/112635024_p0.png",
    "source": "Pixiv"
  },
  {
    "pid": "107085537",
    "title": "ARONA",
    "author": "咔咔",
    "url": "https://i.pixiv.cat/img-original/img/2023/04/11/20/44/34/107085537_p0.jpg",
    "source": "Pixiv"
  },
  {
    "pid": "118485104",
    "title": "BLUE DIARY",
    "author": "晴山_BlueMountain",
    "url": "https://i.pixiv.cat/img-original/img/2024/05/06/13/40/32/118485104_p0.png",
    "source": "Pixiv"
  },
  {
    "pid": "119296081",
    "title": "普拉娜",
    "author": "千代明Kira",
    "url": "https://i.pixiv.cat/img-original/img/2024/06/03/00/30/07/119296081_p0.png",
    "source": "Pixiv"
  },
  {
    "pid": "118788597",
    "title": "プラナちゃん",
    "author": "Hajin",
    "url": "https://i.pixiv.cat/img-original/img/2024/05/17/00/00/17/118788597_p0.png",
    "source": "Pixiv"
  },
  {
    "pid": "106330222",
    "title": "プラナ",
    "author": "ガラッムン！",
    "url": "https://i.pixiv.cat/img-original/img/2023/03/18/19/17/43/106330222_p0.png",
    "source": "Pixiv"
  },
  {
    "pid": "115108048",
    "title": "プラナ",
    "author": "しいびけえ",
    "url": "https://i.pixiv.cat/img-original/img/2024/01/12/20/30/01/115108048_p0.jpg",
    "source": "Pixiv"
  },
  {
    "pid": "117804842",
    "title": "アロプラ✨",
    "author": "赤彩りんご",
    "url": "https://i.pixiv.cat/img-original/img/2024/04/13/19/55/38/117804842_p0.png",
    "source": "Pixiv"
  },
  {
    "pid": "105537933",
    "title": "霞沢ミユ",
    "author": "巻羊",
    "url": "https://i.pixiv.cat/img-original/img/2023/02/20/00/00/51/105537933_p0.jpg",
    "source": "Pixiv"
  },
  {
    "pid": "98963500",
    "title": "ミユ",
    "author": "羽色",
    "url": "https://i.pixiv.cat/img-original/img/2022/06/11/00/30/01/98963500_p0.jpg",
    "source": "Pixiv"
  },
  {
    "pid": "142032989",
    "title": "请不要欺负兔兔",
    "author": "维亦weeyi",
    "url": "https://i.pixiv.cat/img-original/img/2026/03/08/01/21/35/142032989_p0.jpg",
    "source": "Pixiv"
  },
  {
    "pid": "141904733",
    "title": "霞沢 ミユ",
    "author": "MayoriI",
    "url": "https://i.pixiv.cat/img-original/img/2026/03/04/21/14/03/141904733_p0.jpg",
    "source": "Pixiv"
  },
  {
    "pid": "141535871",
    "title": "❄️",
    "author": "Siya",
    "url": "https://i.pixiv.cat/img-original/img/2026/02/23/16/43/13/141535871_p0.jpg",
    "source": "Pixiv"
  },
  {
    "pid": "141468965",
    "title": "に、似合ってる…かな……？",
    "author": "彩ゆき",
    "url": "https://i.pixiv.cat/img-original/img/2026/02/22/02/28/02/141468965_p0.jpg",
    "source": "Pixiv"
  },
  {
    "pid": "140160465",
    "title": "💗ナツ",
    "author": "櫻ノろこ🌸",
    "url": "https://i.pixiv.cat/img-original/img/2026/01/20/12/09/26/140160465_p0.png",
    "source": "Pixiv"
  },
  {
    "pid": "125190130",
    "title": "キサキ🎄💝",
    "author": "バニーキツネ🐰🦊",
    "url": "https://i.pixiv.cat/img-original/img/2024/12/14/23/14/50/125190130_p0.png",
    "source": "Pixiv"
  },
  {
    "pid": "123263950",
    "title": "寝起キサキ",
    "author": "といぺー",
    "url": "https://i.pixiv.cat/img-original/img/2024/10/12/19/30/01/123263950_p0.jpg",
    "source": "Pixiv"
  },
  {
    "pid": "140126722",
    "title": "早瀬ユウカ",
    "author": "原生",
    "url": "https://i.pixiv.cat/img-original/img/2026/01/19/16/18/38/140126722_p0.jpg",
    "source": "Pixiv"
  },
  {
    "pid": "138990512",
    "title": "ユウカ",
    "author": "damcheong",
    "url": "https://i.pixiv.cat/img-original/img/2025/12/24/19/30/46/138990512_p0.jpg",
    "source": "Pixiv"
  },
  {
    "pid": "139788275",
    "title": "ユウカ、怒らないで...╥﹏╥)",
    "author": "Nyvala",
    "url": "https://i.pixiv.cat/img-original/img/2026/01/11/09/30/02/139788275_p0.png",
    "source": "Pixiv"
  },
  {
    "pid": "141173581",
    "title": "Valentine's Day gift",
    "author": "Sakana思乐鱼",
    "url": "https://i.pixiv.cat/img-original/img/2026/02/14/20/24/09/141173581_p0.jpg",
    "source": "Pixiv"
  },
  {
    "pid": "139561718",
    "title": "ブルアカ",
    "author": "MJMax",
    "url": "https://i.pixiv.cat/img-original/img/2026/01/05/19/18/38/139561718_p0.jpg",
    "source": "Pixiv"
  },
  {
    "pid": "142853876",
    "title": "✨",
    "author": "殘夜 ZANYA",
    "url": "https://i.pixiv.cat/img-original/img/2026/03/28/21/04/28/142853876_p0.jpg",
    "source": "Pixiv"
  },
  {
    "pid": "122170040",
    "title": "キキョウ",
    "author": "NeA",
    "url": "https://i.pixiv.cat/img-original/img/2024/09/06/00/00/28/122170040_p0.jpg",
    "source": "Pixiv"
  },
  {
    "pid": "141107209",
    "title": "ユウカ",
    "author": "smong",
    "url": "https://i.pixiv.cat/img-original/img/2026/02/13/09/55/21/141107209_p0.png",
    "source": "Pixiv"
  },
  {
    "pid": "140922738",
    "title": "カヨコ",
    "author": "smong",
    "url": "https://i.pixiv.cat/img-original/img/2026/02/08/15/47/26/140922738_p0.png",
    "source": "Pixiv"
  },
  {
    "pid": "140761981",
    "title": "トキ",
    "author": "smong",
    "url": "https://i.pixiv.cat/img-original/img/2026/02/04/17/47/39/140761981_p0.png",
    "source": "Pixiv"
  },
  {
    "pid": "142668702",
    "title": "nozomi",
    "author": "SeeRo",
    "url": "https://i.pixiv.cat/img-original/img/2026/03/24/00/16/20/142668702_p0.png",
    "source": "Pixiv"
  },
  {
    "pid": "142094661",
    "title": "トキ",
    "author": "白糸",
    "url": "https://i.pixiv.cat/img-original/img/2026/03/09/16/22/47/142094661_p0.jpg",
    "source": "Pixiv"
  },
  {
    "pid": "142412759",
    "title": "无题",
    "author": "lan9798",
    "url": "https://i.pixiv.cat/img-original/img/2026/03/17/19/12/40/142412759_p0.jpg",
    "source": "Pixiv"
  },
  {
    "pid": "142766735",
    "title": "Kazusa",
    "author": "Y1C6",
    "url": "https://i.pixiv.cat/img-original/img/2026/03/26/18/13/14/142766735_p0.png",
    "source": "Pixiv"
  },
  {
    "pid": "129874894",
    "title": "day47",
    "author": "七田のQTian",
    "url": "https://i.pixiv.cat/img-original/img/2025/04/30/19/43/44/129874894_p0.jpg",
    "source": "Pixiv"
  },
  {
    "pid": "117482103",
    "title": "🖤",
    "author": "Ina",
    "url": "https://i.pixiv.cat/img-original/img/2024/04/02/16/15/29/117482103_p0.png",
    "source": "Pixiv"
  },
  {
    "pid": "123689719",
    "title": "💙",
    "author": "Nahaji",
    "url": "https://i.pixiv.cat/img-original/img/2024/10/26/15/21/46/123689719_p0.jpg",
    "source": "Pixiv"
  },
  {
    "pid": "122825482",
    "title": "桐生 キキョウ",
    "author": "はなもち  s0104y",
    "url": "https://i.pixiv.cat/img-original/img/2024/09/28/00/00/03/122825482_p0.jpg",
    "source": "Pixiv"
  },
  {
    "pid": "114170661",
    "title": "キキョウ",
    "author": "Hijo",
    "url": "https://i.pixiv.cat/img-original/img/2023/12/12/20/41/16/114170661_p0.png",
    "source": "Pixiv"
  },
  {
    "pid": "113716958",
    "title": "キキョウ",
    "author": "まふゆゆ",
    "url": "https://i.pixiv.cat/img-original/img/2023/11/26/07/23/08/113716958_p0.jpg",
    "source": "Pixiv"
  },
  {
    "pid": "118415352",
    "title": "濡れてるじゃない…もっとこっち来て💢",
    "author": "ぴっつぁ@新刊＆セットメロン",
    "url": "https://i.pixiv.cat/img-original/img/2024/05/04/12/01/15/118415352_p0.jpg",
    "source": "Pixiv"
  },
  {
    "pid": "116066848",
    "title": "先生、渡したいものがあるんだけど…",
    "author": "ぴっつぁ@新刊＆セットメロン",
    "url": "https://i.pixiv.cat/img-original/img/2024/02/15/00/02/13/116066848_p0.jpg",
    "source": "Pixiv"
  },
  {
    "pid": "129529799",
    "title": "キキョウ☀️",
    "author": "Kurone",
    "url": "https://i.pixiv.cat/img-original/img/2025/04/21/00/02/21/129529799_p0.png",
    "source": "Pixiv"
  },
  {
    "pid": "118009773",
    "title": "私服カズサ",
    "author": "アヤ／Aya",
    "url": "https://i.pixiv.cat/img-original/img/2024/04/20/21/00/22/118009773_p0.png",
    "source": "Pixiv"
  },
  {
    "pid": "130104510",
    "title": "普拉娜",
    "author": "笼茸-lrono",
    "url": "https://i.pixiv.cat/img-original/img/2025/05/06/16/09/07/130104510_p0.jpg",
    "source": "Pixiv"
  },
  {
    "pid": "106693171",
    "title": "アロナとプラナ",
    "author": "SuperPig",
    "url": "https://i.pixiv.cat/img-original/img/2023/03/30/12/54/21/106693171_p0.png",
    "source": "Pixiv"
  },
  {
    "pid": "142267808",
    "title": "イブキ",
    "author": "Halu",
    "url": "https://i.pixiv.cat/img-original/img/2026/03/14/04/35/25/142267808_p0.jpg",
    "source": "Pixiv"
  },
  {
    "pid": "129295857",
    "title": "「見てー！100点だよー！」",
    "author": "Azel",
    "url": "https://i.pixiv.cat/img-original/img/2025/04/14/12/00/07/129295857_p0.jpg",
    "source": "Pixiv"
  },
  {
    "pid": "125333206",
    "title": "GAW!",
    "author": "怪物の住む森",
    "url": "https://i.pixiv.cat/img-original/img/2024/12/19/20/42/43/125333206_p0.png",
    "source": "Pixiv"
  },
  {
    "pid": "125569888",
    "title": "パジャマ（？）イブキ",
    "author": "怪物の住む森",
    "url": "https://i.pixiv.cat/img-original/img/2024/12/26/20/51/06/125569888_p0.png",
    "source": "Pixiv"
  },
  {
    "pid": "116242002",
    "title": "イブキちゃん！",
    "author": "ファガイ",
    "url": "https://i.pixiv.cat/img-original/img/2024/02/20/23/17/08/116242002_p0.jpg",
    "source": "Pixiv"
  },
  {
    "pid": "134112852",
    "title": "💛",
    "author": "アイス",
    "url": "https://i.pixiv.cat/img-original/img/2025/08/20/16/20/01/134112852_p0.png",
    "source": "Pixiv"
  },
  {
    "pid": "131580790",
    "title": "❤️🖤",
    "author": "アイス",
    "url": "https://i.pixiv.cat/img-original/img/2025/06/15/11/33/19/131580790_p0.png",
    "source": "Pixiv"
  },
  {
    "pid": "131580790",
    "title": "❤️🖤",
    "author": "アイス",
    "url": "https://i.pixiv.cat/img-original/img/2025/06/15/11/33/19/131580790_p0.png",
    "source": "Pixiv"
  },
  {
    "pid": "140584866",
    "title": "VS理不尽ゲー",
    "author": "渡コキュー",
    "url": "https://i.pixiv.cat/img-original/img/2026/01/31/12/32/28/140584866_p0.png",
    "source": "Pixiv"
  },
  {
    "pid": "141936332",
    "title": "「すっと待ってだよ、先生～」",
    "author": "ula卷心菜",
    "url": "https://i.pixiv.cat/img-original/img/2026/03/05/18/52/01/141936332_p0.png",
    "source": "Pixiv"
  },
  {
    "pid": "130631382",
    "title": "무제",
    "author": "Von",
    "url": "https://i.pixiv.cat/img-original/img/2025/05/20/23/54/16/130631382_p0.png",
    "source": "Pixiv"
  },
  {
    "pid": "139602699",
    "title": "Tea Party",
    "author": "okutiri",
    "url": "https://i.pixiv.cat/img-original/img/2026/01/06/19/44/37/139602699_p0.png",
    "source": "Pixiv"
  },
  {
    "pid": "105178136",
    "title": "コハル",
    "author": "Nannung",
    "url": "https://i.pixiv.cat/img-original/img/2023/02/08/00/00/31/105178136_p0.png",
    "source": "Pixiv"
  },
  {
    "pid": "109292151",
    "title": "コハル",
    "author": "SuperPig",
    "url": "https://i.pixiv.cat/img-original/img/2023/06/24/10/37/37/109292151_p0.png",
    "source": "Pixiv"
  },
  {
    "pid": "116401538",
    "title": "기어코 페로로질라 인형를 얻어버린 히후미",
    "author": "GADAL",
    "url": "https://i.pixiv.cat/img-original/img/2024/02/26/02/26/42/116401538_p0.png",
    "source": "Pixiv"
  },
  {
    "pid": "118237357",
    "title": "阿慈谷ヒフミ",
    "author": "じぇい。",
    "url": "https://i.pixiv.cat/img-original/img/2024/04/28/18/48/49/118237357_p0.jpg",
    "source": "Pixiv"
  },
  {
    "pid": "137654051",
    "title": "练习14",
    "author": "月見花",
    "url": "https://i.pixiv.cat/img-original/img/2025/11/19/19/25/43/137654051_p0.png",
    "source": "Pixiv"
  },
  {
    "pid": "141348525",
    "title": "伊落マリー🙏",
    "author": "setakman",
    "url": "https://i.pixiv.cat/img-original/img/2026/02/19/00/00/55/141348525_p0.jpg",
    "source": "Pixiv"
  },
  {
    "pid": "130455376",
    "title": "阿慈谷 ヒフミ",
    "author": "みやヨキ",
    "url": "https://i.pixiv.cat/img-original/img/2025/05/16/08/00/13/130455376_p0.png",
    "source": "Pixiv"
  },
  {
    "pid": "109217657",
    "title": "春",
    "author": "Dalian",
    "url": "https://i.pixiv.cat/img-original/img/2023/07/03/09/39/09/109217657_p0.png",
    "source": "Pixiv"
  },
  {
    "pid": "109217657",
    "title": "春",
    "author": "Dalian",
    "url": "https://i.pixiv.cat/img-original/img/2023/07/03/09/39/09/109217657_p0.png",
    "source": "Pixiv"
  },
  {
    "pid": "137919995",
    "title": "无题",
    "author": "星野琉璃",
    "url": "https://i.pixiv.cat/img-original/img/2025/11/26/20/07/04/137919995_p0.png",
    "source": "Pixiv"
  },
  {
    "pid": "140339496",
    "title": "画了小梓",
    "author": "缘千youqia",
    "url": "https://i.pixiv.cat/img-original/img/2026/01/25/01/11/55/140339496_p0.png",
    "source": "Pixiv"
  },
  {
    "pid": "139062485",
    "title": "圣诞快乐！",
    "author": "Ankry",
    "url": "https://i.pixiv.cat/img-original/img/2025/12/25/23/43/15/139062485_p0.png",
    "source": "Pixiv"
  },
  {
    "pid": "124807592",
    "title": "アロナ~",
    "author": "ula卷心菜",
    "url": "https://i.pixiv.cat/img-original/img/2024/12/01/19/16/10/124807592_p0.jpg",
    "source": "Pixiv"
  },
  {
    "pid": "137958217",
    "title": "无题",
    "author": "星野琉璃",
    "url": "https://i.pixiv.cat/img-original/img/2025/11/27/21/22/12/137958217_p0.png",
    "source": "Pixiv"
  },
  {
    "pid": "140900626",
    "title": "プラナ",
    "author": "インデックス",
    "url": "https://i.pixiv.cat/img-original/img/2026/02/08/00/28/43/140900626_p0.png",
    "source": "Pixiv"
  },
  {
    "pid": "115719293",
    "title": "ヒフミ",
    "author": "SuperPig",
    "url": "https://i.pixiv.cat/img-original/img/2024/02/03/12/26/45/115719293_p0.png",
    "source": "Pixiv"
  },
  {
    "pid": "116933218",
    "title": "イロハ",
    "author": "SuperPig",
    "url": "https://i.pixiv.cat/img-original/img/2024/04/12/00/04/37/116933218_p0.png",
    "source": "Pixiv"
  },
  {
    "pid": "115951373",
    "title": "カヨコ",
    "author": "SuperPig",
    "url": "https://i.pixiv.cat/img-original/img/2024/02/11/12/42/55/115951373_p0.png",
    "source": "Pixiv"
  },
  {
    "pid": "131938794",
    "title": "元・鬼方さん",
    "author": "房",
    "url": "https://i.pixiv.cat/img-original/img/2025/06/25/00/00/20/131938794_p0.png",
    "source": "Pixiv"
  },
  {
    "pid": "117397721",
    "title": "カヨコ",
    "author": "ヤン♈️♏️",
    "url": "https://i.pixiv.cat/img-original/img/2024/03/31/00/08/02/117397721_p0.jpg",
    "source": "Pixiv"
  },
  {
    "pid": "133595004",
    "title": "白ワンピカヨコ",
    "author": "蘭",
    "url": "https://i.pixiv.cat/img-original/img/2025/08/07/18/37/51/133595004_p0.png",
    "source": "Pixiv"
  },
  {
    "pid": "130060688",
    "title": "佳代子赏花~",
    "author": "两仪陌",
    "url": "https://i.pixiv.cat/img-original/img/2025/05/05/14/31/49/130060688_p0.jpg",
    "source": "Pixiv"
  },
  {
    "pid": "124456220",
    "title": "カヨコ",
    "author": "GEMB",
    "url": "https://i.pixiv.cat/img-original/img/2024/11/19/23/34/31/124456220_p0.jpg",
    "source": "Pixiv"
  },
  {
    "pid": "116055923",
    "title": "佳代子",
    "author": "帆水母刺身",
    "url": "https://i.pixiv.cat/img-original/img/2024/02/14/20/21/02/116055923_p0.jpg",
    "source": "Pixiv"
  },
  {
    "pid": "126730252",
    "title": "乐队cat",
    "author": "Lucy Romanda",
    "url": "https://i.pixiv.cat/img-original/img/2025/01/30/23/48/54/126730252_p0.jpg",
    "source": "Pixiv"
  },
  {
    "pid": "130399659",
    "title": "杏山和纱",
    "author": "叶明",
    "url": "https://i.pixiv.cat/img-original/img/2025/05/14/19/06/59/130399659_p0.png",
    "source": "Pixiv"
  },
  {
    "pid": "136050466",
    "title": "无题",
    "author": "红糖红豆糯米包",
    "url": "https://i.pixiv.cat/img-original/img/2025/10/09/09/35/21/136050466_p0.png",
    "source": "Pixiv"
  },
  {
    "pid": "118583892",
    "title": "シュガーラッシュ!!!",
    "author": "TokiYanagi",
    "url": "https://i.pixiv.cat/img-original/img/2024/10/21/12/59/52/118583892_p0.png",
    "source": "Pixiv"
  },
  {
    "pid": "141087878",
    "title": "こたつアイス",
    "author": "まれよん",
    "url": "https://i.pixiv.cat/img-original/img/2026/02/12/21/01/22/141087878_p0.png",
    "source": "Pixiv"
  },
  {
    "pid": "111977655",
    "title": "和纱",
    "author": "馒馒",
    "url": "https://i.pixiv.cat/img-original/img/2023/09/24/00/19/05/111977655_p0.png",
    "source": "Pixiv"
  },
  {
    "pid": "115309197",
    "title": "カズサ",
    "author": "のっけ",
    "url": "https://i.pixiv.cat/img-original/img/2024/01/20/00/00/51/115309197_p0.jpg",
    "source": "Pixiv"
  },
  {
    "pid": "117104596",
    "title": "ミヤコ",
    "author": "のっけ",
    "url": "https://i.pixiv.cat/img-original/img/2024/03/21/00/36/27/117104596_p0.jpg",
    "source": "Pixiv"
  },
  {
    "pid": "116470557",
    "title": "先生・・・温めますか？",
    "author": "ミータロー@FANBOX",
    "url": "https://i.pixiv.cat/img-original/img/2024/02/28/20/01/42/116470557_p0.jpg",
    "source": "Pixiv"
  },
  {
    "pid": "109158919",
    "title": "ミヤコ",
    "author": "イコモチ",
    "url": "https://i.pixiv.cat/img-original/img/2023/06/19/19/38/07/109158919_p0.png",
    "source": "Pixiv"
  },
  {
    "pid": "141700539",
    "title": "亚津子",
    "author": "牢卧",
    "url": "https://i.pixiv.cat/img-original/img/2026/02/27/21/20/34/141700539_p0.png",
    "source": "Pixiv"
  },
  {
    "pid": "115319732",
    "title": "秤アツコ",
    "author": "三角函数",
    "url": "https://i.pixiv.cat/img-original/img/2024/01/20/11/11/39/115319732_p0.png",
    "source": "Pixiv"
  },
  {
    "pid": "119227298",
    "title": "アツコ",
    "author": "JOGABI",
    "url": "https://i.pixiv.cat/img-original/img/2024/06/01/00/49/32/119227298_p0.png",
    "source": "Pixiv"
  },
  {
    "pid": "111059911",
    "title": "月暗面",
    "author": "冬灯",
    "url": "https://i.pixiv.cat/img-original/img/2023/08/22/13/13/49/111059911_p0.jpg",
    "source": "Pixiv"
  },
  {
    "pid": "105908417",
    "title": "アリウススクワッド",
    "author": "としぞう",
    "url": "https://i.pixiv.cat/img-original/img/2023/06/12/03/32/45/105908417_p0.jpg",
    "source": "Pixiv"
  },
  {
    "pid": "140160312",
    "title": "秤アツコ",
    "author": "伊玄",
    "url": "https://i.pixiv.cat/img-original/img/2026/01/20/12/02/42/140160312_p0.png",
    "source": "Pixiv"
  },
  {
    "pid": "142886122",
    "title": "アツコ",
    "author": "クロナガスクジラ",
    "url": "https://i.pixiv.cat/img-original/img/2026/03/29/16/19/24/142886122_p0.jpg",
    "source": "Pixiv"
  },
  {
    "pid": "106623171",
    "title": "アツコ",
    "author": "高嶋しょあ",
    "url": "https://i.pixiv.cat/img-original/img/2023/03/28/00/00/13/106623171_p0.png",
    "source": "Pixiv"
  },
  {
    "pid": "142825276",
    "title": "亚津子",
    "author": "阿尼莫",
    "url": "https://i.pixiv.cat/img-original/img/2026/03/28/02/28/21/142825276_p0.jpg",
    "source": "Pixiv"
  },
  {
    "pid": "109220462",
    "title": "シロコ",
    "author": "Bison倉鼠",
    "url": "https://i.pixiv.cat/img-original/img/2023/06/21/22/25/20/109220462_p0.jpg",
    "source": "Pixiv"
  },
  {
    "pid": "110502620",
    "title": "シロコ",
    "author": "Ekita玄",
    "url": "https://i.pixiv.cat/img-original/img/2023/08/04/00/00/35/110502620_p0.jpg",
    "source": "Pixiv"
  },
  {
    "pid": "140731512",
    "title": "お花見休憩 / Hanami Break",
    "author": "汐",
    "url": "https://i.pixiv.cat/img-original/img/2026/02/03/21/15/18/140731512_p0.png",
    "source": "Pixiv"
  },
  {
    "pid": "129058432",
    "title": "シロコ",
    "author": "いわし",
    "url": "https://i.pixiv.cat/img-original/img/2025/04/07/17/35/11/129058432_p0.jpg",
    "source": "Pixiv"
  },
  {
    "pid": "125903796",
    "title": "ホシノ",
    "author": "いわし",
    "url": "https://i.pixiv.cat/img-original/img/2025/01/04/22/35/48/125903796_p0.jpg",
    "source": "Pixiv"
  },
  {
    "pid": "137132407",
    "title": "ホシノ",
    "author": "和菓子",
    "url": "https://i.pixiv.cat/img-original/img/2025/11/05/21/39/38/137132407_p0.png",
    "source": "Pixiv"
  },
  {
    "pid": "136764517",
    "title": "小鳥遊 ホシノ",
    "author": "回旋镖打自己",
    "url": "https://i.pixiv.cat/img-original/img/2025/10/27/18/32/18/136764517_p0.jpg",
    "source": "Pixiv"
  },
  {
    "pid": "135274084",
    "title": "🍧🐋💛💙🍧",
    "author": "百山百",
    "url": "https://i.pixiv.cat/img-original/img/2025/09/19/11/42/41/135274084_p0.jpg",
    "source": "Pixiv"
  },
  {
    "pid": "135612061",
    "title": "ホシノ",
    "author": "Mana",
    "url": "https://i.pixiv.cat/img-original/img/2025/09/28/00/00/20/135612061_p0.jpg",
    "source": "Pixiv"
  },
  {
    "pid": "130124445",
    "title": "Day28 ホシノ",
    "author": "南条まや",
    "url": "https://i.pixiv.cat/img-original/img/2025/05/07/00/00/11/130124445_p0.jpg",
    "source": "Pixiv"
  },
  {
    "pid": "142813514",
    "title": "Kazusa",
    "author": "anon",
    "url": "https://i.pixiv.cat/img-original/img/2026/03/27/21/48/53/142813514_p0.jpg",
    "source": "Pixiv"
  }
]